upset_enrich/__init__.py
upset_enrich/upset_enrich.py
upset_enrich-0.0.1.dist-info/licenses/LICENSE
upset_enrich-0.0.1.dist-info/METADATA
upset_enrich-0.0.1.dist-info/WHEEL
upset_enrich-0.0.1.dist-info/entry_points.txt
upset_enrich-0.0.1.dist-info/top_level.txt
upset_enrich-0.0.1.dist-info/RECORD
