Metadata-Version: 2.4
Name: upset_enrich
Version: 0.0.1
Summary: UpSet plots with upsetplot package, with added highlighting of sets for which overlap between all pairs of component input sets is significant
Author-email: Nathan Schaefer <nathan.schaefer@ucsf.edu>
License: MIT License
Project-URL: homepage, https://github.com/nkschaefer/upset_enrich
Classifier: Development Status :: 3 - Alpha
Classifier: Operating System :: OS Independent
Classifier: Programming Language :: Python :: 3
License-File: LICENSE
Requires-Dist: setuptools
Requires-Dist: pandas
Requires-Dist: numpy
Requires-Dist: matplotlib
Requires-Dist: scipy>=1.7.0
Requires-Dist: upsetplot>=0.9.0
Dynamic: license-file
